webexteamsarchiver/__init__.py
webexteamsarchiver/jinja_env.py
webexteamsarchiver/webexteamsarchiver.py
webexteamsarchiver/static/.DS_Store
webexteamsarchiver/static/.css/bootstrap.min.css
webexteamsarchiver/static/.css/featherlight.min.css
webexteamsarchiver/static/.css/fonts.css
webexteamsarchiver/static/.css/teams.css
webexteamsarchiver/static/.fonts/collab-ui-icons-28119b2a06bcd7daada5d307c874de91.woff2
webexteamsarchiver/static/.fonts/collab-ui-icons-4ad727153f66e210ad5a9f842acccaad.woff
webexteamsarchiver/static/.fonts/Roboto/LICENSE.txt
webexteamsarchiver/static/.fonts/Roboto/Roboto-Black.ttf
webexteamsarchiver/static/.fonts/Roboto/Roboto-BlackItalic.ttf
webexteamsarchiver/static/.fonts/Roboto/Roboto-Bold.ttf
webexteamsarchiver/static/.fonts/Roboto/Roboto-BoldItalic.ttf
webexteamsarchiver/static/.fonts/Roboto/Roboto-Italic.ttf
webexteamsarchiver/static/.fonts/Roboto/Roboto-Light.ttf
webexteamsarchiver/static/.fonts/Roboto/Roboto-LightItalic.ttf
webexteamsarchiver/static/.fonts/Roboto/Roboto-Medium.ttf
webexteamsarchiver/static/.fonts/Roboto/Roboto-MediumItalic.ttf
webexteamsarchiver/static/.fonts/Roboto/Roboto-Regular.ttf
webexteamsarchiver/static/.fonts/Roboto/Roboto-Thin.ttf
webexteamsarchiver/static/.fonts/Roboto/Roboto-ThinItalic.ttf
webexteamsarchiver/static/.images/icon.png
webexteamsarchiver/static/.js/featherlight.min.js
webexteamsarchiver/static/.js/jquery.min.js
webexteamsarchiver/templates/default.html
webexteamsarchiver/templates/default.txt
webexteamsarchiver/templates/header.html
webexteamsarchiver/templates/room_content.html
webexteamsarchiver-0.11.3.dist-info/LICENSE
webexteamsarchiver-0.11.3.dist-info/METADATA
webexteamsarchiver-0.11.3.dist-info/WHEEL
webexteamsarchiver-0.11.3.dist-info/top_level.txt
webexteamsarchiver-0.11.3.dist-info/RECORD
