Metadata-Version: 2.1
Name: webexteamsarchiver
Version: 0.11.3
Summary: Room archiver utility for Webex Teams
Home-page: https://github.com/CiscoDevNet/webex-teams-archiver
Author: Felipe de Mello
Author-email: fdemello@cisco.com
License: MIT; Copyright (c) 2018 Cisco Systems, Inc.
Keywords: cisco webex teams spark python messaging
Platform: UNKNOWN
Classifier: Development Status :: 4 - Beta
Classifier: Intended Audience :: System Administrators
Classifier: Intended Audience :: Telecommunications Industry
Classifier: Intended Audience :: Information Technology
Classifier: Natural Language :: English
Classifier: License :: OSI Approved :: MIT License
Classifier: Programming Language :: Python :: 3
Classifier: Programming Language :: Python :: 3.5
Classifier: Programming Language :: Python :: 3.6
Classifier: Programming Language :: Python :: 3.7
Classifier: Topic :: Communications
Classifier: Topic :: Communications :: Chat
License-File: LICENSE
Requires-Dist: webexteamssdk
Requires-Dist: jinja2
Requires-Dist: requests
Requires-Dist: hurry.filesize
Requires-Dist: bump2version
